ga_test_cython/__init__.py
ga_test_cython/matrix_product.py
ga_test_cython/operations_utils/__init__.py
ga_test_cython/operations_utils/dot_product_utils.pyx
ga_test_cython-0.1.0a7.dist-info/LICENSE
ga_test_cython-0.1.0a7.dist-info/METADATA
ga_test_cython-0.1.0a7.dist-info/WHEEL
ga_test_cython-0.1.0a7.dist-info/RECORD
