Metadata-Version: 2.1
Name: ga_test_cython
Version: 0.1.0a7
Summary: An tiny example of GitHub Actions + Poetry + Cython
Author: Christian Pieringer
Author-email: cppierin@uc.cl
Requires-Python: >=3.10
Classifier: Programming Language :: Python :: 3
Classifier: Programming Language :: Python :: 3.10
Classifier: Programming Language :: Python :: 3.11
Classifier: Programming Language :: Python :: 3.12
Requires-Dist: Cython (>=3.0.0)
Requires-Dist: numpy (>=2.0.1,<3.0.0)
